setup.py
bin/textplot
textplot/__init__.py
textplot/graphs.py
textplot/helpers.py
textplot/matrix.py
textplot/text.py
textplot/utils.py
textplot.egg-info/PKG-INFO
textplot.egg-info/SOURCES.txt
textplot.egg-info/dependency_links.txt
textplot.egg-info/requires.txt
textplot.egg-info/top_level.txt
textplot/data/stopwords.txt