Metadata-Version: 1.0
Name: textplot
Version: 0.1.1
Summary: (Mental) maps of texts.
Home-page: https://github.com/davidmcclure/textplot
Author: David McClure
Author-email: davidwilliammcclure@gmail.com
License: MIT
Platform: UNKNOWN
